DataGenerator/CSVReader.py
DataGenerator/Column.py
DataGenerator/Databases.py
DataGenerator/Generators.py
DataGenerator/Query.py
DataGenerator/Table.py
DataGenerator/__init__.py
DatabaseDataGenerator-1.7.0.dist-info/LICENSE
DatabaseDataGenerator-1.7.0.dist-info/METADATA
DatabaseDataGenerator-1.7.0.dist-info/WHEEL
DatabaseDataGenerator-1.7.0.dist-info/top_level.txt
DatabaseDataGenerator-1.7.0.dist-info/RECORD
