Metadata-Version: 2.1
Name: DatabaseDataGenerator
Version: 1.7.0
Summary: Generates any amount of data for supported databases (currently postgresql and sqlite)
Home-page: https://github.com/PhatDave/DatabaseDataGenerator
Author: PhatDave
Author-email: kosmodiskclassic0@gmail.com
Project-URL: Bug Tracker, https://github.com/PhatDave/DatabaseDataGenerator/issues
Classifier: Programming Language :: Python :: 3
Classifier: License :: OSI Approved :: MIT License
Classifier: Operating System :: OS Independent
Requires-Python: >=3.6
License-File: LICENSE
Requires-Dist: Faker (>=11.3.0)
Requires-Dist: psycopg2 (>=2.9.3)
Requires-Dist: python-dateutil (>=2.8.2)
Requires-Dist: six (>=1.16.0)
Requires-Dist: text-unidecode (>=1.3)
Requires-Dist: faker-vehicle (>=0.2.0)
Requires-Dist: tqdm (>=4.62.3)
